LiteBuild/build_engine.py
LiteBuild/build_logger.py
LiteBuild/build_workers.py
LiteBuild/command_generator.py
LiteBuild/config_loader.py
LiteBuild/dependency_graph.py
LiteBuild/lite_build_controller.py
LiteBuild/lite_build_runner.py
LiteBuild/litebuild.py
LiteBuild/schema.py
docs/readme.md
litebuild-0.4.1.dist-info/licenses/LICENSE
litebuild-0.4.1.dist-info/METADATA
litebuild-0.4.1.dist-info/WHEEL
litebuild-0.4.1.dist-info/entry_points.txt
litebuild-0.4.1.dist-info/top_level.txt
litebuild-0.4.1.dist-info/RECORD
