Metadata-Version: 2.4
Name: LiteBuild
Version: 0.4.1
Summary: Lightweight build engine
Author: corb
License: Copyright 2025 corb555
Project-URL: Repository, https://github.com/corb555/LiteBuild
Classifier: Intended Audience :: Developers
Classifier: Topic :: Scientific/Engineering :: GIS
Classifier: Operating System :: POSIX :: Linux
Classifier: Operating System :: MacOS
Requires-Python: >=3.9
License-File: LICENSE
Requires-Dist: Cerberus>=1.3.7
Requires-Dist: networkx>=3.5
Requires-Dist: filelock>=3.20.0
Requires-Dist: pandas>=2.2.3
Requires-Dist: YMLEditor>=1.7.1
Dynamic: license-file
